pyabf/__init__.py
pyabf/abf.py
pyabf/abfReader.py
pyabf/abfWriter.py
pyabf/atf.py
pyabf/filter.py
pyabf/names.py
pyabf/plot.py
pyabf/stimulus.py
pyabf/waveform.py
pyabf/abf1/__init__.py
pyabf/abf1/headerV1.py
pyabf/abf2/__init__.py
pyabf/abf2/adcSection.py
pyabf/abf2/dacSection.py
pyabf/abf2/dataSection.py
pyabf/abf2/epochPerDacSection.py
pyabf/abf2/epochSection.py
pyabf/abf2/headerV2.py
pyabf/abf2/protocolSection.py
pyabf/abf2/section.py
pyabf/abf2/stringsSection.py
pyabf/abf2/synchArraySection.py
pyabf/abf2/tagSection.py
pyabf/abf2/userListSection.py
pyabf/tools/__init__.py
pyabf/tools/abfHeaderDisplay.py
pyabf/tools/ap.py
pyabf/tools/generate.py
pyabf/tools/memtest.py
pyabf/tools/memtestMath.py
pyabf/tools/sweep.py
pyabf-2.3.8.dist-info/LICENSE
pyabf-2.3.8.dist-info/METADATA
pyabf-2.3.8.dist-info/WHEEL
pyabf-2.3.8.dist-info/top_level.txt
pyabf-2.3.8.dist-info/RECORD
