Metadata-Version: 2.1
Name: pyabf
Version: 2.3.8
Summary: Python library for reading files in Axon Binary Format (ABF)
Home-page: http://swharden.com/pyabf
Author: Scott W Harden
Author-email: SWHarden@gmail.com
License: MIT License
Project-URL: Bug Reports, https://github.com/swharden/pyABF/issues
Project-URL: Source, https://github.com/swharden/pyABF
Project-URL: Documentation, https://swharden.com/pyabf/tutorial
Platform: any
Classifier: Programming Language :: Python :: 3
Classifier: Natural Language :: English
Classifier: License :: OSI Approved :: MIT License
Classifier: Operating System :: OS Independent
Classifier: Intended Audience :: Developers
Classifier: Intended Audience :: Science/Research
Classifier: Topic :: Scientific/Engineering :: Bio-Informatics
Classifier: Topic :: Scientific/Engineering :: Information Analysis
Classifier: Topic :: Scientific/Engineering :: Medical Science Apps.
Classifier: Topic :: Scientific/Engineering :: Visualization
Classifier: Topic :: Software Development :: Libraries :: Python Modules
Classifier: Topic :: Software Development :: Libraries :: Application Frameworks
Requires-Python: >=3.8
License-File: LICENSE
